{
  "$schema": "https://developer.microsoft.com/json-schemas/fabric/item/report/definition/visualContainer/2.6.0/schema.json",
  "name": "0f39a066c20318a6aeb6",
  "position": {
    "x": 0,
    "y": 0,
    "z": 0,
    "height": 563.55971896955509,
    "width": 721.43637782982046,
    "tabOrder": 0
  },
  "visual": {
    "visualType": "donutChart",
    "query": {
      "queryState": {
        "Category": {
          "projections": [
            {
              "field": {
                "Column": {
                  "Expression": {
                    "SourceRef": {
                      "Entity": "buildings"
                    }
                  },
                  "Property": "building_simplified"
                }
              },
              "queryRef": "buildings.building_simplified",
              "nativeQueryRef": "building_simplified",
              "active": true
            }
          ]
        },
        "Y": {
          "projections": [
            {
              "field": {
                "Aggregation": {
                  "Expression": {
                    "Column": {
                      "Expression": {
                        "SourceRef": {
                          "Entity": "buildings"
                        }
                      },
                      "Property": "gross"
                    }
                  },
                  "Function": 0
                }
              },
              "queryRef": "Sum(buildings.gross)",
              "nativeQueryRef": "Sum of gross"
            }
          ]
        }
      },
      "sortDefinition": {
        "sort": [
          {
            "field": {
              "Aggregation": {
                "Expression": {
                  "Column": {
                    "Expression": {
                      "SourceRef": {
                        "Entity": "buildings"
                      }
                    },
                    "Property": "gross"
                  }
                },
                "Function": 0
              }
            },
            "direction": "Descending"
          }
        ],
        "isDefaultSort": true
      }
    },
    "drillFilterOtherVisuals": true
  }
}